<?xml version="1.0" encoding="utf-8" ?>
<dwsync>
<file name="about_us.php" server="ec2-13-59-42-198.us-east-2.compute.amazonaws.com//var/www/html/" local="133734906400000000" remote="133742609010000000" Dst="2" />
<file name="account_settings.php" server="ec2-13-59-42-198.us-east-2.compute.amazonaws.com//var/www/html/" local="133712381293939974" remote="133742609020000000" Dst="2" />
<file name="contact_us.php" server="ec2-13-59-42-198.us-east-2.compute.amazonaws.com//var/www/html/" local="133712381294113288" remote="133742609030000000" Dst="2" />
<file name="dashboard.php" server="ec2-13-59-42-198.us-east-2.compute.amazonaws.com//var/www/html/" local="133712381294298957" remote="133742609030000000" Dst="2" />
<file name="faq.php" server="ec2-13-59-42-198.us-east-2.compute.amazonaws.com//var/www/html/" local="133712381294468982" remote="133742609030000000" Dst="2" />
<file name="find_volunteer_opportunities.php" server="ec2-13-59-42-198.us-east-2.compute.amazonaws.com//var/www/html/" local="133712381294657324" remote="133742609030000000" Dst="2" />
<file name="index.php" server="ec2-13-59-42-198.us-east-2.compute.amazonaws.com//var/www/html/" local="133744467971436168" remote="133744467970000000" Dst="2" />
<file name="organization_dashboard.php" server="ec2-13-59-42-198.us-east-2.compute.amazonaws.com//var/www/html/" local="133712381294972674" remote="133742609050000000" Dst="2" />
<file name="post_event.php" server="ec2-13-59-42-198.us-east-2.compute.amazonaws.com//var/www/html/" local="133712381295157106" remote="133742609050000000" Dst="2" />
<file name="signin.php" server="ec2-13-59-42-198.us-east-2.compute.amazonaws.com//var/www/html/" local="133744467983425512" remote="133744467980000000" Dst="2" />
<file name="functions.php" server="ec2-13-59-42-198.us-east-2.compute.amazonaws.com//var/www/html/" local="133744467961673713" remote="133744467960000000" Dst="2" />
<file name="navigation.php" server="ec2-13-59-42-198.us-east-2.compute.amazonaws.com//var/www/html/" local="133744467980789288" remote="133744467980000000" Dst="2" />
<file name="signup.php" server="ec2-13-59-42-198.us-east-2.compute.amazonaws.com//var/www/html/" local="133744498967174711" remote="133744498970000000" Dst="2" />
<file name="home.php" server="ec2-13-59-42-198.us-east-2.compute.amazonaws.com//var/www/html/" local="133744375418507243" remote="133744427640000000" Dst="2" />
<file name="logout.php" server="ec2-13-59-42-198.us-east-2.compute.amazonaws.com//var/www/html/" local="133744467978131972" remote="133744467980000000" Dst="2" />
</dwsync>